LICENSE
README.md
pyproject.toml
setup.py
firewxpy/NWS_Forecasts.py
firewxpy/RTMA.py
firewxpy/SPC_Outlook_Graphics.py
firewxpy/__init__.py
firewxpy/calc.py
firewxpy/colormaps.py
firewxpy/cross_sections.py
firewxpy/data_access.py
firewxpy/dims.py
firewxpy/forecast_models.py
firewxpy/fuels_graphics.py
firewxpy/geometry.py
firewxpy/observations.py
firewxpy/parsers.py
firewxpy/raws_sigs.py
firewxpy/sawti.py
firewxpy/settings.py
firewxpy/solar_information.py
firewxpy/soundings.py
firewxpy/standard.py
firewxpy/utilities.py
firewxpy.egg-info/PKG-INFO
firewxpy.egg-info/SOURCES.txt
firewxpy.egg-info/dependency_links.txt
firewxpy.egg-info/requires.txt
firewxpy.egg-info/top_level.txt