Metadata-Version: 2.1
Name: firewxpy
Version: 1.6.5
Summary: Weather Analysis and Forecasting For Fire Weather
Author: Eric J Drewitz, USDA/USFS
Keywords: meteorology,science,data-analysis,weather,forecasting
Classifier: Programming Language :: Python
Classifier: Topic :: Scientific/Engineering
Classifier: Topic :: Scientific/Engineering :: Atmospheric Science
Classifier: Operating System :: OS Independent
Classifier: License :: OSI Approved :: MIT License
Requires-Python: >=3.10
License-File: LICENSE
Requires-Dist: matplotlib>=3.7
Requires-Dist: protobuf>=3.20.3
Requires-Dist: metpy>=1.5.1
Requires-Dist: netcdf4>=1.7.1
Requires-Dist: numpy>=1.24
Requires-Dist: pandas>=2.2
Requires-Dist: siphon>=0.10.0
Requires-Dist: xarray>=2023.1.0
Requires-Dist: pysolar>=0.11
Requires-Dist: cfgrib>=0.9.10.4
Requires-Dist: cartopy>=0.21.0
Requires-Dist: pytz>=2024.1
Requires-Dist: xeofs>=3.0.4
Requires-Dist: geopandas>=1.1.0
